queuinx/__init__.py
queuinx/__main__.py
queuinx/models.py
queuinx/network.py
queuinx/test_example.py
queuinx/utils.py
queuinx/experimental/__init__.py
queuinx/experimental/models.py
queuinx/queuing_theory/__init__.py
queuinx/queuing_theory/basic.py
queuinx/queuing_theory/mm1.py
queuinx/queuing_theory/mm1b.py
queuinx-0.0.2.dist-info/METADATA
queuinx-0.0.2.dist-info/WHEEL
queuinx-0.0.2.dist-info/licenses/LICENSE
queuinx-0.0.2.dist-info/RECORD
