Metadata-Version: 2.4
Name: queuinx
Version: 0.0.2
Summary: Queuinx: A library for performance evaluation in Jax
Project-URL: Homepage, https://github.com/krzysztofrusek/queuinx
Author-email: Krzysztof Rusek <krussek@gmail.com>
License:                                  Apache License
License-File: LICENSE
Keywords: buffer,graph,jax,machine learning,networking,networks,neural,python,queuing theory
Classifier: Development Status :: 3 - Alpha
Classifier: Environment :: Console
Classifier: Intended Audience :: Developers
Classifier: Intended Audience :: Science/Research
Classifier: Intended Audience :: Telecommunications Industry
Classifier: License :: OSI Approved :: Apache Software License
Classifier: Operating System :: OS Independent
Classifier: Programming Language :: Python
Classifier: Programming Language :: Python :: 3
Classifier: Topic :: Scientific/Engineering
Classifier: Topic :: Scientific/Engineering :: Artificial Intelligence
Classifier: Topic :: Software Development :: Libraries :: Python Modules
Classifier: Topic :: System :: Networking
Requires-Python: >=3.10
Requires-Dist: chex>=0.1.5
Requires-Dist: distrax>=0.1.2
Requires-Dist: jax>=0.6.0
Requires-Dist: jaxlib>=0.6.0
Requires-Dist: jaxopt>=0.5.5
